flask_auth_sys/__init__.py
flask_auth_sys/main.py
flask_auth_system-0.0.2.dist-info/METADATA
flask_auth_system-0.0.2.dist-info/WHEEL
flask_auth_system-0.0.2.dist-info/top_level.txt
flask_auth_system-0.0.2.dist-info/RECORD
